{"updated":"2026-07-22T15:45:36.451Z","station":"Backyard Station","current":{"outdoor":{"temperature":{"time":"1784735082","unit":"℃","value":"4.9"},"feels_like":{"time":"1784735082","unit":"℃","value":"4.9"},"app_temp":{"time":"1784735082","unit":"℃","value":"3.7"},"dew_point":{"time":"1784735082","unit":"℃","value":"4.6"},"vpd":{"time":"1784735082","unit":"inHg","value":"0.005"},"humidity":{"time":"1784735082","unit":"%","value":"98"}},"indoor":{"temperature":{"time":"1784735082","unit":"℃","value":"20.9"},"humidity":{"time":"1784735082","unit":"%","value":"55"},"dew_point":{"time":"1784735082","unit":"℃","value":"11.6"},"feels_like":{"time":"1784735082","unit":"℃","value":"20.9"},"app_tempin":{"time":"1784735082","unit":"℃","value":"21.4"}},"solar_and_uvi":{"solar":{"time":"1784735082","unit":"W/m²","value":"0.0"},"uvi":{"time":"1784735082","unit":"","value":"0"}},"rainfall":{"rain_rate":{"time":"1784735082","unit":"mm/hr","value":"0.0"},"daily":{"time":"1784735082","unit":"mm","value":"0.0"},"event":{"time":"1784735082","unit":"mm","value":"0.0"},"1_hour":{"time":"1784735082","unit":"mm","value":"0.0"},"24_hours":{"time":"1784735082","unit":"mm","value":"0.0"},"weekly":{"time":"1784735082","unit":"mm","value":"4.1"},"monthly":{"time":"1784735082","unit":"mm","value":"64.3"},"yearly":{"time":"1784735082","unit":"mm","value":"368.9"}},"wind":{"wind_speed":{"time":"1784735082","unit":"km/h","value":"0.0"},"wind_gust":{"time":"1784735082","unit":"km/h","value":"0.0"},"wind_direction":{"time":"1784735082","unit":"º","value":"94"},"10_minute_average_wind_direction":{"time":"1784735082","unit":"º","value":"94"}},"pressure":{"relative":{"time":"1784735082","unit":"hPa","value":"1029.6"},"absolute":{"time":"1784735082","unit":"hPa","value":"1029.6"}},"temp_and_humidity_ch1":{"temperature":{"time":"1784735082","unit":"℃","value":"19.2"},"humidity":{"time":"1784735082","unit":"%","value":"58"}},"temp_and_humidity_ch2":{"temperature":{"time":"1784735082","unit":"℃","value":"21.4"},"humidity":{"time":"1784735082","unit":"%","value":"59"}},"battery":{"sensor_array":{"time":"1784735082","unit":"","value":"0"},"temp_humidity_sensor_ch1":{"time":"1784735082","unit":"","value":"0"},"temp_humidity_sensor_ch2":{"time":"1784735082","unit":"","value":"0"}},"AC1100-0000325F":{"daily":{"value":"4.07","unit":"kW·h","day":"20260722"},"monthly":{"value":"137","unit":"kW·h","month":"202607"},"status":{"value":1,"unit":"","time":"1784735047"},"power":{"value":"365","unit":"W","time":"1784735082"},"voltage":{"value":"229","unit":"V","time":"1784735082"}},"AC1100-00003268":{"daily":{"value":"11.2","unit":"kW·h","day":"20260722"},"monthly":{"value":"271.2","unit":"kW·h","month":"202607"},"status":{"value":1,"unit":"","time":"1784735008"},"power":{"value":"1.08","unit":"kW","time":"1784735082"},"voltage":{"value":"237","unit":"V","time":"1784735082"}}},"history":[{"t":1784652333,"temp":4.3,"rd":0},{"t":1784652634,"temp":4.3,"rd":0},{"t":1784652925,"temp":4.4,"rd":0},{"t":1784653251,"temp":4.5,"rd":0},{"t":1784653525,"temp":4.5,"rd":0},{"t":1784653830,"temp":4.7,"rd":0},{"t":1784654131,"temp":4.7,"rd":0},{"t":1784654434,"temp":4.6,"rd":0},{"t":1784654727,"temp":4.5,"rd":0},{"t":1784655043,"temp":4.3,"rd":0},{"t":1784655327,"temp":4.3,"rd":0},{"t":1784655635,"temp":4.3,"rd":0},{"t":1784655933,"temp":4.2,"rd":0},{"t":1784656236,"temp":4.2,"rd":0},{"t":1784656524,"temp":4.2,"rd":0},{"t":1784656637,"temp":4.1,"rd":0},{"t":1784656851,"temp":3.9,"rd":0},{"t":1784657128,"temp":3.8,"rd":0},{"t":1784657435,"temp":3.8,"rd":0},{"t":1784657733,"temp":3.8,"rd":0},{"t":1784658032,"temp":3.7,"rd":0},{"t":1784658326,"temp":3.6,"rd":0},{"t":1784658643,"temp":3.7,"rd":0},{"t":1784659093,"temp":3.6,"rd":0},{"t":1784659233,"temp":3.4,"rd":0},{"t":1784659530,"temp":3.5,"rd":0},{"t":1784659834,"temp":3.6,"rd":0},{"t":1784660128,"temp":3.6,"rd":0},{"t":1784660452,"temp":3.6,"rd":0},{"t":1784660730,"temp":3.6,"rd":0},{"t":1784661034,"temp":3.6,"rd":0},{"t":1784661332,"temp":3.4,"rd":0},{"t":1784661636,"temp":3.5,"rd":0},{"t":1784661932,"temp":3.3,"rd":0},{"t":1784662244,"temp":3.2,"rd":0},{"t":1784662526,"temp":3.2,"rd":0},{"t":1784662592,"temp":3.2,"rd":0},{"t":1784662830,"temp":3.2,"rd":0},{"t":1784663133,"temp":3,"rd":0},{"t":1784663432,"temp":3.2,"rd":0},{"t":1784663727,"temp":3.2,"rd":0},{"t":1784664052,"temp":3.2,"rd":0},{"t":1784664326,"temp":3.2,"rd":0},{"t":1784664632,"temp":3,"rd":0},{"t":1784664931,"temp":3,"rd":0},{"t":1784665233,"temp":3.2,"rd":0},{"t":1784665529,"temp":3.2,"rd":0},{"t":1784665843,"temp":3.4,"rd":0},{"t":1784666125,"temp":3.6,"rd":0},{"t":1784666434,"temp":3.9,"rd":0},{"t":1784666734,"temp":4.1,"rd":0},{"t":1784666855,"temp":4.2,"rd":0},{"t":1784667032,"temp":4.3,"rd":0},{"t":1784667325,"temp":4.4,"rd":0},{"t":1784667650,"temp":4.5,"rd":0},{"t":1784667927,"temp":4.6,"rd":0},{"t":1784668234,"temp":4.6,"rd":0},{"t":1784668531,"temp":4.5,"rd":0},{"t":1784668834,"temp":4.5,"rd":0},{"t":1784669127,"temp":4.4,"rd":0},{"t":1784669439,"temp":4.3,"rd":0},{"t":1784669725,"temp":4.2,"rd":0},{"t":1784670034,"temp":4,"rd":0},{"t":1784670330,"temp":3.9,"rd":0},{"t":1784670456,"temp":3.8,"rd":0},{"t":1784670629,"temp":3.8,"rd":0},{"t":1784670927,"temp":3.6,"rd":0},{"t":1784671246,"temp":3.6,"rd":0},{"t":1784671528,"temp":3.6,"rd":0},{"t":1784671831,"temp":3.5,"rd":0},{"t":1784672130,"temp":3.3,"rd":0},{"t":1784672431,"temp":3.2,"rd":0},{"t":1784672724,"temp":3.1,"rd":0},{"t":1784673040,"temp":3,"rd":0},{"t":1784673328,"temp":2.9,"rd":0},{"t":1784673583,"temp":3,"rd":0},{"t":1784673634,"temp":3,"rd":0},{"t":1784673928,"temp":2.9,"rd":0},{"t":1784674233,"temp":2.8,"rd":0},{"t":1784674528,"temp":2.5,"rd":0},{"t":1784674849,"temp":2.6,"rd":0},{"t":1784675127,"temp":2.8,"rd":0},{"t":1784675434,"temp":3,"rd":0},{"t":1784675729,"temp":3.1,"rd":0},{"t":1784676032,"temp":3.3,"rd":0},{"t":1784676325,"temp":3.5,"rd":0},{"t":1784676640,"temp":3.7,"rd":0},{"t":1784676927,"temp":3.8,"rd":0},{"t":1784677230,"temp":4,"rd":0},{"t":1784677246,"temp":4,"rd":0},{"t":1784677530,"temp":4.1,"rd":0},{"t":1784677830,"temp":4.3,"rd":0},{"t":1784678123,"temp":4.4,"rd":0},{"t":1784678450,"temp":4.5,"rd":0},{"t":1784678725,"temp":4.5,"rd":0},{"t":1784679032,"temp":4.7,"rd":0},{"t":1784679331,"temp":4.9,"rd":0},{"t":1784679633,"temp":5.2,"rd":0},{"t":1784679927,"temp":5.3,"rd":0},{"t":1784680240,"temp":5.4,"rd":0},{"t":1784680525,"temp":5.5,"rd":0},{"t":1784680831,"temp":5.8,"rd":0},{"t":1784681129,"temp":6.1,"rd":0},{"t":1784681437,"temp":6.1,"rd":0},{"t":1784681727,"temp":6.3,"rd":0},{"t":1784682048,"temp":6.6,"rd":0},{"t":1784682327,"temp":6.8,"rd":0},{"t":1784682420,"temp":6.9,"rd":0},{"t":1784682630,"temp":7,"rd":0},{"t":1784682932,"temp":7.3,"rd":0},{"t":1784683235,"temp":7.3,"rd":0},{"t":1784683525,"temp":7.4,"rd":0},{"t":1784683839,"temp":7.7,"rd":0},{"t":1784684128,"temp":8,"rd":0},{"t":1784684429,"temp":8.1,"rd":0},{"t":1784684730,"temp":8.5,"rd":0},{"t":1784685033,"temp":9.4,"rd":0},{"t":1784685324,"temp":9.7,"rd":0},{"t":1784685645,"temp":10.8,"rd":0},{"t":1784685927,"temp":10.8,"rd":0},{"t":1784686230,"temp":11.8,"rd":0},{"t":1784686529,"temp":12.4,"rd":0},{"t":1784686832,"temp":12.1,"rd":0},{"t":1784687124,"temp":11.8,"rd":0},{"t":1784687440,"temp":12.6,"rd":0},{"t":1784687726,"temp":12.3,"rd":0},{"t":1784688035,"temp":12.8,"rd":0},{"t":1784688328,"temp":13,"rd":0},{"t":1784688630,"temp":13,"rd":0},{"t":1784688923,"temp":13.5,"rd":0},{"t":1784689245,"temp":13.9,"rd":0},{"t":1784689529,"temp":14.4,"rd":0},{"t":1784689829,"temp":14.3,"rd":0},{"t":1784690131,"temp":14.8,"rd":0},{"t":1784690432,"temp":15.9,"rd":0},{"t":1784690726,"temp":15.7,"rd":0},{"t":1784691039,"temp":15.1,"rd":0},{"t":1784691327,"temp":15,"rd":0},{"t":1784691632,"temp":14.7,"rd":0},{"t":1784691929,"temp":14.8,"rd":0},{"t":1784692231,"temp":14.6,"rd":0},{"t":1784692526,"temp":14.6,"rd":0},{"t":1784692846,"temp":15.6,"rd":0},{"t":1784693124,"temp":15.9,"rd":0},{"t":1784693430,"temp":15.5,"rd":0},{"t":1784693728,"temp":14.9,"rd":0},{"t":1784694032,"temp":15.3,"rd":0},{"t":1784694326,"temp":16.1,"rd":0},{"t":1784694639,"temp":16.4,"rd":0},{"t":1784694924,"temp":16.3,"rd":0},{"t":1784695229,"temp":15.6,"rd":0},{"t":1784695529,"temp":15.3,"rd":0},{"t":1784695833,"temp":15.8,"rd":0},{"t":1784696125,"temp":15.9,"rd":0},{"t":1784696446,"temp":15.5,"rd":0},{"t":1784696723,"temp":15.7,"rd":0},{"t":1784697035,"temp":15.5,"rd":0},{"t":1784697330,"temp":15.4,"rd":0},{"t":1784697631,"temp":15.2,"rd":0},{"t":1784697927,"temp":15.3,"rd":0},{"t":1784698240,"temp":15.9,"rd":0},{"t":1784698527,"temp":16.3,"rd":0},{"t":1784698830,"temp":16.6,"rd":0},{"t":1784699129,"temp":16.6,"rd":0},{"t":1784699430,"temp":16.9,"rd":0},{"t":1784699727,"temp":16.6,"rd":0},{"t":1784700048,"temp":16.5,"rd":0},{"t":1784700325,"temp":16.1,"rd":0},{"t":1784700630,"temp":15.8,"rd":0},{"t":1784700928,"temp":15.7,"rd":0},{"t":1784701230,"temp":15.8,"rd":0},{"t":1784701524,"temp":16.6,"rd":0},{"t":1784701842,"temp":16.3,"rd":0},{"t":1784702128,"temp":15.9,"rd":0},{"t":1784702434,"temp":16,"rd":0},{"t":1784702729,"temp":16.1,"rd":0},{"t":1784703031,"temp":15.7,"rd":0},{"t":1784703327,"temp":15.6,"rd":0},{"t":1784703649,"temp":15.3,"rd":0},{"t":1784703926,"temp":15.4,"rd":0},{"t":1784704236,"temp":15.7,"rd":0},{"t":1784704533,"temp":16.2,"rd":0},{"t":1784704549,"temp":16.2,"rd":0},{"t":1784704836,"temp":15.8,"rd":0},{"t":1784705127,"temp":15.4,"rd":0},{"t":1784705440,"temp":15,"rd":0},{"t":1784705728,"temp":14.9,"rd":0},{"t":1784706035,"temp":15.9,"rd":0},{"t":1784706333,"temp":16.1,"rd":0},{"t":1784706634,"temp":16.3,"rd":0},{"t":1784706929,"temp":16.1,"rd":0},{"t":1784707250,"temp":15.9,"rd":0},{"t":1784707527,"temp":15.7,"rd":0},{"t":1784707832,"temp":15.5,"rd":0},{"t":1784708133,"temp":15.4,"rd":0},{"t":1784708431,"temp":15.2,"rd":0},{"t":1784708727,"temp":15.2,"rd":0},{"t":1784709041,"temp":15.1,"rd":0},{"t":1784709326,"temp":15,"rd":0},{"t":1784709633,"temp":14.8,"rd":0},{"t":1784709932,"temp":14.7,"rd":0},{"t":1784710231,"temp":14.7,"rd":0},{"t":1784710527,"temp":14.5,"rd":0},{"t":1784710848,"temp":14.3,"rd":0},{"t":1784711127,"temp":14,"rd":0},{"t":1784711437,"temp":13.6,"rd":0},{"t":1784711734,"temp":13.2,"rd":0},{"t":1784712031,"temp":12.8,"rd":0},{"t":1784712328,"temp":12.1,"rd":0},{"t":1784712639,"temp":11.3,"rd":0},{"t":1784712925,"temp":10.9,"rd":0},{"t":1784713234,"temp":10.6,"rd":0},{"t":1784713302,"temp":10.4,"rd":0},{"t":1784713532,"temp":10.2,"rd":0},{"t":1784713832,"temp":9.9,"rd":0},{"t":1784714126,"temp":9.7,"rd":0},{"t":1784714452,"temp":9.4,"rd":0},{"t":1784714728,"temp":9.3,"rd":0},{"t":1784715033,"temp":9.1,"rd":0},{"t":1784715330,"temp":8.9,"rd":0},{"t":1784715631,"temp":8.8,"rd":0},{"t":1784715926,"temp":8.5,"rd":0},{"t":1784716238,"temp":8.3,"rd":0},{"t":1784716528,"temp":8.2,"rd":0},{"t":1784716831,"temp":8.1,"rd":0},{"t":1784717130,"temp":8,"rd":0},{"t":1784717432,"temp":7.7,"rd":0},{"t":1784717726,"temp":7.7,"rd":0},{"t":1784718047,"temp":7.6,"rd":0},{"t":1784718327,"temp":7.5,"rd":0},{"t":1784718632,"temp":7.5,"rd":0},{"t":1784718932,"temp":7.5,"rd":0},{"t":1784719232,"temp":7.3,"rd":0},{"t":1784719525,"temp":7.1,"rd":0},{"t":1784719815,"temp":6.9,"rd":0},{"t":1784719841,"temp":6.9,"rd":0},{"t":1784720124,"temp":6.6,"rd":0},{"t":1784720430,"temp":6.4,"rd":0},{"t":1784720731,"temp":6.4,"rd":0},{"t":1784721031,"temp":6.2,"rd":0},{"t":1784721324,"temp":6.2,"rd":0},{"t":1784721651,"temp":6.3,"rd":0},{"t":1784721926,"temp":6.4,"rd":0},{"t":1784722231,"temp":6.4,"rd":0},{"t":1784722534,"temp":6.3,"rd":0},{"t":1784722835,"temp":6.1,"rd":0},{"t":1784723126,"temp":6.1,"rd":0},{"t":1784723440,"temp":6,"rd":0},{"t":1784723725,"temp":5.9,"rd":0},{"t":1784724032,"temp":6,"rd":0},{"t":1784724333,"temp":6,"rd":0},{"t":1784724633,"temp":6,"rd":0},{"t":1784724925,"temp":5.8,"rd":0},{"t":1784725249,"temp":5.7,"rd":0},{"t":1784725513,"temp":5.6,"rd":0},{"t":1784725831,"temp":5.4,"rd":0},{"t":1784726130,"temp":5.3,"rd":0},{"t":1784726436,"temp":5.2,"rd":0},{"t":1784726728,"temp":5.5,"rd":0},{"t":1784727043,"temp":5.5,"rd":0},{"t":1784727330,"temp":5.5,"rd":0},{"t":1784727636,"temp":5.5,"rd":0},{"t":1784727935,"temp":5.6,"rd":0},{"t":1784728232,"temp":5.5,"rd":0},{"t":1784728528,"temp":5.4,"rd":0},{"t":1784728851,"temp":5.5,"rd":0},{"t":1784729129,"temp":5.5,"rd":0},{"t":1784729440,"temp":5.6,"rd":0},{"t":1784729731,"temp":5.6,"rd":0},{"t":1784730035,"temp":5.5,"rd":0},{"t":1784730328,"temp":5.6,"rd":0},{"t":1784730643,"temp":5.6,"rd":0},{"t":1784730926,"temp":5.5,"rd":0},{"t":1784731235,"temp":5.4,"rd":0},{"t":1784731531,"temp":5.4,"rd":0},{"t":1784731838,"temp":5.6,"rd":0},{"t":1784732128,"temp":5.6,"rd":0},{"t":1784732453,"temp":5.6,"rd":0},{"t":1784732729,"temp":5.5,"rd":0},{"t":1784733035,"temp":5.6,"rd":0},{"t":1784733134,"temp":5.5,"rd":0},{"t":1784733330,"temp":5.5,"rd":0},{"t":1784733635,"temp":5.4,"rd":0},{"t":1784733926,"temp":5.3,"rd":0},{"t":1784734251,"temp":5.2,"rd":0},{"t":1784734532,"temp":5,"rd":0},{"t":1784734833,"temp":5,"rd":0},{"t":1784735136,"temp":4.9,"rd":0}]}